test/__init__.py
test/check_train_valid_spk.py
test/test.py
test/wada_snr.py
vocex/__init__.py
vocex/conformer_layer.py
vocex/conformer_model.py
vocex/image_helpers.py
vocex/onnx_stft.py
vocex/pooling.py
vocex/scaler.py
vocex/softdtw.py
vocex/speaker_loss.py
vocex/transformer.py
vocex/utils.py
vocex-0.1.11.dist-info/METADATA
vocex-0.1.11.dist-info/RECORD
vocex-0.1.11.dist-info/WHEEL
vocex-0.1.11.dist-info/metadata.json
vocex-0.1.11.dist-info/top_level.txt
