Metadata-Version: 2.0
Name: vocex
Version: 0.1.11
Summary: Voice Frame-Level and Utterance-Level Attribute Extraction
Author: Christoph Minixhofer
Author-email: christoph.minixhofer@gmail.com
License: MIT
Requires-Python: >=3.6
Requires-Dist: torchaudio>=0.8.0
Requires-Dist: librosa>=0.8.0
Requires-Dist: numpy>=1.19.0
Requires-Dist: tqdm>=4.48.2
Requires-Dist: transformers>=4.0.0
Requires-Dist: torchaudio (>=0.8.0)
Requires-Dist: librosa (>=0.8.0)
Requires-Dist: numpy (>=1.19.0)
Requires-Dist: tqdm (>=4.48.2)
Requires-Dist: transformers (>=4.0.0)
